{
  "project_info": {
    "project_number": "496312482624",
    "project_id": "guru2-10daf",
    "storage_bucket": "guru2-10daf.appspot.com"
  },
  "client": [
    {
      "client_info": {
        "mobilesdk_app_id": "1:496312482624:android:105660ff7930dbd8d418a5",
        "android_client_info": {
          "package_name": "com.example.guru30realreal_app"
        }
      },
      "oauth_client": [
        {
          "client_id": "496312482624-qfelpvr2rhhf8o8dpr8gb3hq4t7v6nul.apps.googleusercontent.com",
          "client_type": 3
        }
      ],
      "api_key": [
        {
          "current_key": "AIzaSyBkezZU5dERCa_KtY11noQ8m5yKJ-zGJaw"
        }
      ],
      "services": {
        "appinvite_service": {
          "other_platform_oauth_client": [
            {
              "client_id": "496312482624-qfelpvr2rhhf8o8dpr8gb3hq4t7v6nul.apps.googleusercontent.com",
              "client_type": 3
            }
          ]
        }
      }
    }
  ],
  "configuration_version": "1"
}